jsonModel/__init__.py
jsonModel/decoder.py
jsonModel/encoder.py
pyjsonmodel-1.0.2.dist-info/LICENCE
pyjsonmodel-1.0.2.dist-info/METADATA
pyjsonmodel-1.0.2.dist-info/WHEEL
pyjsonmodel-1.0.2.dist-info/top_level.txt
pyjsonmodel-1.0.2.dist-info/zip-safe
pyjsonmodel-1.0.2.dist-info/RECORD
